{
  "name" : "SkOrder",
  "originTableName" : "sk_order",
  "comment" : null,
  "fullColumn" : [ {
    "name" : "id",
    "comment" : null,
    "type" : null,
    "shortType" : null,
    "ktShortType" : "Long",
    "custom" : false,
    "ext" : { }
  }, {
    "name" : "userId",
    "comment" : null,
    "type" : null,
    "shortType" : null,
    "ktShortType" : "Long",
    "custom" : false,
    "ext" : { }
  }, {
    "name" : "orderId",
    "comment" : null,
    "type" : null,
    "shortType" : null,
    "ktShortType" : "Long",
    "custom" : false,
    "ext" : { }
  }, {
    "name" : "goodsId",
    "comment" : null,
    "type" : null,
    "shortType" : null,
    "ktShortType" : "Long",
    "custom" : false,
    "ext" : { }
  } ],
  "pkColumn" : null,
  "otherColumn" : null,
  "savePackageName" : "com.example.miaosha",
  "savePath" : "./src/main/java/com/example/miaosha",
  "saveModelName" : "miaosha"
}